configs/config.yaml
datasets/__init__.py
datasets/base.py
datasets/registry.py
examples/00_data_exploration.py
examples/01_load_grlite_model.py
examples/02_model_evaluation.py
examples/03_custom_model.py
look_bench-0.3.0.dist-info/licenses/LICENSE
metrics/__init__.py
metrics/base.py
metrics/factory.py
metrics/map.py
metrics/mrr.py
metrics/ndcg.py
metrics/rank.py
models/__init__.py
models/base.py
models/clip_model.py
models/dinov2_model.py
models/factory.py
models/grlite_model.py
models/registry.py
models/siglip_model.py
runner/__init__.py
runner/base_pipeline.py
runner/evaluation_pipeline.py
runner/evaluator.py
runner/feature_extraction_pipeline.py
runner/pipeline.py
runner/runner.py
scripts/example_dataset_converter.py
utils/__init__.py
utils/hf_loader.py
utils/logging.py
look_bench-0.3.0.dist-info/METADATA
look_bench-0.3.0.dist-info/WHEEL
look_bench-0.3.0.dist-info/top_level.txt
look_bench-0.3.0.dist-info/RECORD
