Metadata-Version: 2.4
Name: look-bench
Version: 0.3.0
Summary: A live, holistic, and challenging benchmark for fashion image retrieval in real e-commerce settings
Author: LookBench Team
License-Expression: Apache-2.0
Project-URL: Homepage, https://github.com/SerendipityOneInc/look-bench
Project-URL: Documentation, https://serendipityoneinc.github.io/look-bench-page/
Project-URL: Repository, https://github.com/SerendipityOneInc/look-bench
Project-URL: Bug Tracker, https://github.com/SerendipityOneInc/look-bench/issues
Keywords: fashion,image-retrieval,benchmark,evaluation,computer-vision
Classifier: Development Status :: 4 - Beta
Classifier: Intended Audience :: Developers
Classifier: Intended Audience :: Science/Research
Classifier: Operating System :: OS Independent
Classifier: Programming Language :: Python :: 3
Classifier: Programming Language :: Python :: 3.8
Classifier: Programming Language :: Python :: 3.9
Classifier: Programming Language :: Python :: 3.10
Classifier: Programming Language :: Python :: 3.11
Classifier: Topic :: Scientific/Engineering :: Artificial Intelligence
Classifier: Topic :: Software Development :: Libraries :: Python Modules
Requires-Python: >=3.8
License-File: LICENSE
Requires-Dist: torch>=2.0.0
Requires-Dist: torchvision>=0.15.0
Requires-Dist: transformers>=4.30.0
Requires-Dist: datasets>=2.14.0
Requires-Dist: numpy>=1.24.0
Requires-Dist: pandas>=2.0.0
Requires-Dist: pyarrow>=12.0.0
Requires-Dist: Pillow>=9.5.0
Requires-Dist: PyYAML>=6.0
Requires-Dist: tqdm>=4.65.0
Provides-Extra: dev
Requires-Dist: pytest>=7.3.0; extra == "dev"
Requires-Dist: black>=23.3.0; extra == "dev"
Requires-Dist: flake8>=6.0.0; extra == "dev"
Requires-Dist: mypy>=1.3.0; extra == "dev"
Provides-Extra: advanced
Requires-Dist: timm>=0.9.0; extra == "advanced"
Requires-Dist: open-clip-torch>=2.20.0; extra == "advanced"
Provides-Extra: examples
Requires-Dist: matplotlib>=3.5.0; extra == "examples"
Dynamic: license-file
